.readthedocs.yml
LICENSE
README.rst
pyproject.toml
docs/owls_demo.png
owls_app/__init__.py
owls_app/abstract.txt
owls_app/app.py
owls_app/cli.py
owls_app/solara.css
owls_app/version.py
owls_app.egg-info/PKG-INFO
owls_app.egg-info/SOURCES.txt
owls_app.egg-info/dependency_links.txt
owls_app.egg-info/entry_points.txt
owls_app.egg-info/requires.txt
owls_app.egg-info/top_level.txt