Metadata-Version: 2.4
Name: owls-app
Version: 0.2
Summary: Olin Wilson Legacy Survey
Author-email: Brett Morris <morrisbrettm@gmail.com>
License: MIT License
Project-URL: repository, https://github.com/bmorris3/owls-app
License-File: LICENSE
Requires-Dist: matplotlib
Requires-Dist: solara
Requires-Dist: ipywidgets
Requires-Dist: numpy
Requires-Dist: astropy
Requires-Dist: astroquery
Requires-Dist: expecto
Requires-Dist: specutils
Requires-Dist: pandas
Requires-Dist: lcviz>=1.1.1
Requires-Dist: specutils
Requires-Dist: aesop-arces
Dynamic: license-file
